blockchain_simulator/__init__.py
blockchain_simulator/_metadata.py
blockchain_simulator/block.py
blockchain_simulator/blockchain.py
blockchain_simulator/blueprint.py
blockchain_simulator/broadcast.py
blockchain_simulator/consensus.py
blockchain_simulator/example.py
blockchain_simulator/examples/__init__.py
blockchain_simulator/examples/animation_events.json
blockchain_simulator/examples/blockchain_simulator/manim_animator.py
blockchain_simulator/examples/run_simulations.py
blockchain_simulator/manim_animator.py
blockchain_simulator/network_topology.py
blockchain_simulator/node.py
blockchain_simulator/simulator.py
blockchain_simulator/validator.py
blockchain_simulator/visualizer.py
blockchain_simulator-0.1.4.dist-info/LICENSE
blockchain_simulator-0.1.4.dist-info/METADATA
blockchain_simulator-0.1.4.dist-info/WHEEL
blockchain_simulator-0.1.4.dist-info/RECORD
